[
  {
    "name": "Ferrari 488 GT3 Zolder",
    "carModel": "ferrari-488-gt3",
    "carClass": "GT3",
    "trackName": "Zolder",
    "downloadUrl": "https://www.youtube.com/watch?v=CUFIeo4oWVI",
    "videoUrl": "https://www.youtube.com/watch?v=CUFIeo4oWVI",
    "pageUrl": "https://accsetups.com/free-setups/for/ferrari-488-gt3/on/zolder",
    "author": "PS_Racing",
    "lapTime": "1:26.912",
    "date": "2025-12",
    "hasRace": true,
    "hasQuali": false,
    "hasSafe": false,
    "hasWet": false
  }
]