[
  {
    "team": "Ferrari",
    "author": "SimRacingSetup",
    "videoUrl": "https://www.youtube.com/watch?v=8n8xtXwah8E",
    "lapTime": "1:15.879",
    "sessionType": "",
    "inputDevice": "wheel",
    "weather": "Dry",
    "setup": {
      "frontWing": 29,
      "rearWing": 29,
      "diffOnThrottle": 45,
      "diffOffThrottle": 25,
      "frontCamber": -3.5,
      "rearCamber": -2,
      "frontToe": 0,
      "rearToe": 0.1,
      "frontSuspension": 37,
      "rearSuspension": 4,
      "frontAntiRollBar": 15,
      "rearAntiRollBar": 20,
      "frontRideHeight": 22,
      "rearRideHeight": 50,
      "brakePressure": 100,
      "frontBrakeBias": 53,
      "frontRightTyrePressure": 28.5,
      "frontLeftTyrePressure": 28.5,
      "rearRightTyrePressure": 25.5,
      "rearLeftTyrePressure": 25.5
    },
    "source": "https://simracingsetup.com/setups/f1-25-setups/mexican-grand-prix-2025-ferrari-dry-115-879/",
    "provider": "simracingsetup"
  },
  {
    "team": "Ferrari",
    "author": "SimRacingSetup",
    "videoUrl": "",
    "lapTime": "1:14.626",
    "sessionType": "",
    "inputDevice": "wheel",
    "weather": "Dry",
    "setup": {
      "frontWing": 40,
      "rearWing": 34,
      "diffOnThrottle": 100,
      "diffOffThrottle": 35,
      "frontCamber": -3.5,
      "rearCamber": -2,
      "frontToe": 0,
      "rearToe": 0.1,
      "frontSuspension": 32,
      "rearSuspension": 1,
      "frontAntiRollBar": 9,
      "rearAntiRollBar": 21,
      "frontRideHeight": 23,
      "rearRideHeight": 45,
      "brakePressure": 100,
      "frontBrakeBias": 53,
      "frontRightTyrePressure": 24.2,
      "frontLeftTyrePressure": 24.2,
      "rearRightTyrePressure": 20.5,
      "rearLeftTyrePressure": 20.5
    },
    "source": "https://simracingsetup.com/setups/f1-25-setups/mexican-grand-prix-2025-ferrari-dry-114-626/",
    "provider": "simracingsetup"
  },
  {
    "team": "Kick Sauber",
    "author": "SimRacingSetup",
    "videoUrl": "",
    "lapTime": "1:15.568",
    "sessionType": "",
    "inputDevice": "controller",
    "weather": "Dry",
    "setup": {
      "frontWing": 29,
      "rearWing": 29,
      "diffOnThrottle": 60,
      "diffOffThrottle": 50,
      "frontCamber": -3.1,
      "rearCamber": -1.5,
      "frontToe": 0.13,
      "rearToe": 0.19,
      "frontSuspension": 27,
      "rearSuspension": 22,
      "frontAntiRollBar": 16,
      "rearAntiRollBar": 13,
      "frontRideHeight": 22,
      "rearRideHeight": 50,
      "brakePressure": 99,
      "frontBrakeBias": 56,
      "frontRightTyrePressure": 24,
      "frontLeftTyrePressure": 24,
      "rearRightTyrePressure": 24.5,
      "rearLeftTyrePressure": 25
    },
    "source": "https://simracingsetup.com/setups/f1-25-setups/mexican-grand-prix-2025-kick-sauber-dry-115568/",
    "provider": "simracingsetup"
  },
  {
    "team": "Racing Bulls",
    "author": "SimRacingSetup",
    "videoUrl": "",
    "lapTime": "1:15.336",
    "sessionType": "",
    "inputDevice": "wheel",
    "weather": "Dry",
    "setup": {
      "frontWing": 35,
      "rearWing": 42,
      "diffOnThrottle": 100,
      "diffOffThrottle": 20,
      "frontCamber": -3.5,
      "rearCamber": -2,
      "frontToe": 0,
      "rearToe": 0.1,
      "frontSuspension": 41,
      "rearSuspension": 2,
      "frontAntiRollBar": 4,
      "rearAntiRollBar": 21,
      "frontRideHeight": 21,
      "rearRideHeight": 52,
      "brakePressure": 100,
      "frontBrakeBias": 55,
      "frontRightTyrePressure": 24.1,
      "frontLeftTyrePressure": 24.1,
      "rearRightTyrePressure": 22,
      "rearLeftTyrePressure": 22
    },
    "source": "https://simracingsetup.com/setups/f1-25-setups/mexican-grand-prix-2025-racing-bulls-dry-115-336/",
    "provider": "simracingsetup"
  },
  {
    "team": "McLaren",
    "author": "SimRacingSetup",
    "videoUrl": "",
    "lapTime": "1:15.987",
    "sessionType": "",
    "inputDevice": "controller",
    "weather": "Dry",
    "setup": {
      "frontWing": 20,
      "rearWing": 16,
      "diffOnThrottle": 100,
      "diffOffThrottle": 35,
      "frontCamber": -3.5,
      "rearCamber": -1.9,
      "frontToe": 0,
      "rearToe": 0.12,
      "frontSuspension": 32,
      "rearSuspension": 3,
      "frontAntiRollBar": 5,
      "rearAntiRollBar": 21,
      "frontRideHeight": 23,
      "rearRideHeight": 45,
      "brakePressure": 90,
      "frontBrakeBias": 56,
      "frontRightTyrePressure": 29.5,
      "frontLeftTyrePressure": 29.5,
      "rearRightTyrePressure": 26.5,
      "rearLeftTyrePressure": 26.5
    },
    "source": "https://simracingsetup.com/setups/f1-25-setups/mexican-grand-prix-2025-mclaren-dry-115-987/",
    "provider": "simracingsetup"
  }
]