[
  {
    "name": "BMW M6 GT3 Watkins Glen",
    "carModel": "bmw-m6-gt3-1",
    "carClass": "GT3",
    "trackName": "Watkins Glen",
    "downloadUrl": "https://www.youtube.com/watch?v=rfLy9vzvP8I",
    "videoUrl": "https://www.youtube.com/watch?v=rfLy9vzvP8I",
    "pageUrl": "https://accsetups.com/free-setups/for/bmw-m6-gt3-1/on/watkins-glen",
    "author": "Ohne Speed",
    "lapTime": "",
    "date": "2025-04",
    "hasRace": true,
    "hasQuali": true,
    "hasSafe": false,
    "hasWet": false
  }
]